{
  "id": "standard",
  "plants": [
    { "number": 3, "type": "thermal", "fuel": 2, "powers": 1, "name": "老舊火力機櫃" },
    { "number": 4, "type": "hydro", "fuel": 2, "powers": 1, "name": "水冷試驗機房" },
    { "number": 5, "type": "hybrid", "fuel": 2, "powers": 1, "name": "混供中繼站" },
    { "number": 6, "type": "waste", "fuel": 1, "powers": 1, "name": "單機廢料爐" },
    { "number": 7, "type": "thermal", "fuel": 3, "powers": 2, "name": "燃氣運算棚" },
    { "number": 8, "type": "hydro", "fuel": 3, "powers": 2, "name": "溪流水輪機房" },
    { "number": 9, "type": "thermal", "fuel": 1, "powers": 1, "name": "屋頂日光機櫃" },
    { "number": 10, "type": "hydro", "fuel": 2, "powers": 2, "name": "河谷水冷中心" },
    { "number": 11, "type": "quantum", "fuel": 1, "powers": 2, "name": "初代量子實驗艙" },
    { "number": 12, "type": "hybrid", "fuel": 2, "powers": 2, "name": "雙迴路混供站" },
    { "number": 13, "type": "self", "fuel": 0, "powers": 1, "name": "微型綠能節點" },
    { "number": 14, "type": "waste", "fuel": 2, "powers": 2, "name": "雙爐廢料精煉站" },
    { "number": 15, "type": "hydro", "fuel": 2, "powers": 3, "name": "攔河堰資料中心" },
    { "number": 16, "type": "thermal", "fuel": 2, "powers": 3, "name": "聚光太陽能塔" },
    { "number": 17, "type": "quantum", "fuel": 1, "powers": 2, "name": "低溫量子機櫃" },
    { "number": 18, "type": "self", "fuel": 0, "powers": 2, "name": "離網自持聚落" },
    { "number": 19, "type": "waste", "fuel": 2, "powers": 3, "name": "近港廢料處理廠" },
    { "number": 20, "type": "hydro", "fuel": 3, "powers": 5, "name": "大壩渦輪機廠" },
    { "number": 21, "type": "hybrid", "fuel": 2, "powers": 4, "name": "複合能源樞紐" },
    { "number": 22, "type": "self", "fuel": 0, "powers": 2, "name": "被動冷卻塔" },
    { "number": 23, "type": "quantum", "fuel": 1, "powers": 3, "name": "量子退火陣列" },
    { "number": 24, "type": "waste", "fuel": 2, "powers": 4, "name": "離岸廢料熔煉台" },
    { "number": 25, "type": "hydro", "fuel": 2, "powers": 5, "name": "深水冷卻園區" },
    { "number": 26, "type": "thermal", "fuel": 2, "powers": 5, "name": "沙漠日光電廠" },
    { "number": 27, "type": "self", "fuel": 0, "powers": 3, "name": "地熱自持基地" },
    { "number": 28, "type": "quantum", "fuel": 1, "powers": 4, "name": "光子量子矩陣" },
    { "number": 29, "type": "hybrid", "fuel": 1, "powers": 4, "name": "智慧調度中心" },
    { "number": 30, "type": "waste", "fuel": 3, "powers": 6, "name": "巨型廢料再生廠" },
    { "number": 31, "type": "hydro", "fuel": 3, "powers": 6, "name": "抽蓄水力要塞" },
    { "number": 32, "type": "thermal", "fuel": 3, "powers": 6, "name": "軌道鏡面聚能站" },
    { "number": 33, "type": "self", "fuel": 0, "powers": 4, "name": "零碳園區" },
    { "number": 34, "type": "quantum", "fuel": 1, "powers": 5, "name": "量子叢集主機" },
    { "number": 35, "type": "thermal", "fuel": 1, "powers": 5, "name": "高效日光穹頂" },
    { "number": 36, "type": "hydro", "fuel": 3, "powers": 7, "name": "峽谷超級大壩" },
    { "number": 37, "type": "self", "fuel": 0, "powers": 4, "name": "仿生自持網" },
    { "number": 38, "type": "waste", "fuel": 3, "powers": 7, "name": "大陸級廢料回收網" },
    { "number": 39, "type": "quantum", "fuel": 1, "powers": 6, "name": "容錯量子核心" },
    { "number": 40, "type": "thermal", "fuel": 2, "powers": 6, "name": "熔鹽儲能電站" },
    { "number": 42, "type": "hydro", "fuel": 2, "powers": 6, "name": "海嶺潮汐矩陣" },
    { "number": 44, "type": "self", "fuel": 0, "powers": 5, "name": "戴森原型節點" },
    { "number": 46, "type": "hybrid", "fuel": 3, "powers": 7, "name": "全域能源中樞" },
    { "number": 50, "type": "fusion", "fuel": 0, "powers": 6, "name": "奇點核心" }
  ],
  "setup": {
    "initial_market": [3, 4, 5, 6],
    "initial_future": [7, 8, 9, 10],
    "top_of_deck": 13,
    "step3_at_bottom": true
  }
}
